adaptive_dataset/__init__.py
adaptive_dataset-0.1.1.dist-info/METADATA
adaptive_dataset-0.1.1.dist-info/WHEEL
adaptive_dataset-0.1.1.dist-info/top_level.txt
adaptive_dataset-0.1.1.dist-info/RECORD
