Metadata-Version: 2.1
Name: adaptive-dataset
Version: 0.1.1
Summary: Demo library
Home-page: UNKNOWN
Author: KhoiDOO
Author-email: khoido8899@gmail.com
License: MIT
Platform: UNKNOWN
Classifier: Intended Audience :: Developers
Classifier: License :: OSI Approved :: MIT License
Classifier: Programming Language :: Python
Classifier: Programming Language :: Python :: 3
Classifier: Programming Language :: Python :: 3.6
Classifier: Programming Language :: Python :: 3.7
Classifier: Programming Language :: Python :: 3.8
Classifier: Programming Language :: Python :: 3.9
Classifier: Operating System :: OS Independent
Requires-Dist: pandas
Requires-Dist: opencv-python (==4.6.0.66)
Requires-Dist: deeplake[enterprise]
Requires-Dist: albumentations
